{
  "10": [
    {
      "name": "Digital Door",
      "twitter": "",
      "discord": "",
      "start_timestamp": 1672967970610
    },
    {
      "name": "Crypto Snack",
      "twitter": "",
      "discord": "",
      "start_timestamp": 1636737244985
    },
    {
      "name": "Arturas",
      "twitter": "",
      "discord": "",
      "start_timestamp": 1593679726511
    },
    {
      "name": "Achim Domma",
      "twitter": "achimdomma",
      "discord": "",
      "start_timestamp": 1588926903248
    },
    {
      "name": "Maurice Perry",
      "twitter": "",
      "discord": "",
      "start_timestamp": 1575826633076
    },
    {
      "name": "Dodzidenu Dzakuma",
      "twitter": "",
      "discord": "nexocentric#0434",
      "start_timestamp": 1572836840820
    },
    {
      "name": "xvxx",
      "twitter": "",
      "discord": "",
      "start_timestamp": 1572311879973
    },
    {
      "name": "Florian Neumann",
      "twitter": "FlorianBreisch",
      "discord": "florian_neumann#7165",
      "start_timestamp": 1568874287443
    },
    {
      "name": "JustBoil.me ",
      "twitter": "",
      "discord": "",
      "start_timestamp": 1566299949150
    },
    {
      "name": "Marozed ",
      "twitter": "",
      "discord": "",
      "start_timestamp": 1554644489695
    },
    {
      "name": "Tyler Weeres",
      "twitter": "tweeres04",
      "discord": "",
      "start_timestamp": 1552764835672
    },
    {
      "name": "Al Romano",
      "twitter": "",
      "discord": "",
      "start_timestamp": 1551649687685
    },
    {
      "name": "Ian Ebden",
      "twitter": "",
      "discord": "",
      "start_timestamp": 1550700350622
    },
    {
      "name": "GameTop.com ",
      "twitter": "",
      "discord": "",
      "start_timestamp": 1547543775155
    },
    {
      "name": "Mae van Dijk",
      "twitter": "",
      "discord": "",
      "start_timestamp": 1545250051380
    },
    {
      "name": "Luis Castro Martín",
      "twitter": "",
      "discord": "",
      "start_timestamp": 1541171212880
    },
    {
      "name": "Franz Geffke",
      "twitter": "f_anzs",
      "discord": "",
      "start_timestamp": 1534701757930
    },
    {
      "name": "Millie Lin",
      "twitter": "",
      "discord": "",
      "start_timestamp": 1534580207167
    },
    {
      "name": "Jason Seminara",
      "twitter": "",
      "discord": "",
      "start_timestamp": 1532955289949
    },
    {
      "name": "Marcel Schiering",
      "twitter": "",
      "discord": "",
      "start_timestamp": 1530361790433
    },
    {
      "name": "Daniel Zavala",
      "twitter": "Siedrix",
      "discord": "",
      "start_timestamp": 1529716263081
    },
    {
      "name": "Charles Treece",
      "twitter": "charlestreece",
      "discord": "",
      "start_timestamp": 1529691809367
    },
    {
      "name": "Dmitry Malyshev",
      "twitter": "",
      "discord": "",
      "start_timestamp": 1527750137010
    },
    {
      "name": "Stuart Stanfield",
      "twitter": "",
      "discord": "Tashiketh#7466",
      "start_timestamp": 1527579663355
    },
    {
      "name": "Heli Herrera",
      "twitter": "",
      "discord": "",
      "start_timestamp": 1521355127164
    },
    {
      "name": "Tőrös Egon Richárd",
      "twitter": "",
      "discord": "",
      "start_timestamp": 1518689634542
    },
    {
      "name": "Jan Kremlacek",
      "twitter": "jankremlacek",
      "discord": "",
      "start_timestamp": 1515677659602
    },
    {
      "name": "Patrick Cool",
      "twitter": "",
      "discord": "",
      "start_timestamp": 1515628908009
    },
    {
      "name": "Stanley Eosakul",
      "twitter": "",
      "discord": "Stanza987#8058",
      "start_timestamp": 1515262177708
    },
    {
      "name": "Emil S",
      "twitter": "",
      "discord": "",
      "start_timestamp": 1514840896323
    },
    {
      "name": "Luis Guillermo Moreno",
      "twitter": "",
      "discord": "",
      "start_timestamp": 1512875878046
    },
    {
      "name": "Takayuki Yamaguchi",
      "twitter": "takyam",
      "discord": "",
      "start_timestamp": 1512366265358
    },
    {
      "name": "Leo Zeba",
      "twitter": "leozeba",
      "discord": "",
      "start_timestamp": 1511898573597
    },
    {
      "name": "Kyu ",
      "twitter": "",
      "discord": "",
      "start_timestamp": 1511206454450
    },
    {
      "name": "Matt Swan",
      "twitter": "",
      "discord": "",
      "start_timestamp": 1511195163646
    },
    {
      "name": "MrG0lden ",
      "twitter": "mrg0lden",
      "discord": "",
      "start_timestamp": 1510912862566
    },
    {
      "name": "Jordan Nemrow",
      "twitter": "",
      "discord": "",
      "start_timestamp": 1510767260223
    },
    {
      "name": "Niklas ",
      "twitter": "paradoxxger",
      "discord": "",
      "start_timestamp": 1510740078593
    },
    {
      "name": "dansup ",
      "twitter": "",
      "discord": "dansup#9699",
      "start_timestamp": 1510690234523
    },
    {
      "name": "Wikiki ",
      "twitter": "",
      "discord": "",
      "start_timestamp": 1510677732534
    },
    {
      "name": "Peter Ryszkiewicz",
      "twitter": "",
      "discord": "",
      "start_timestamp": 1510668549717
    },
    {
      "name": "Michael Schinis",
      "twitter": "",
      "discord": "",
      "start_timestamp": 1510582549865
    }
  ],
  "30": [
    {
      "name": "Maia!",
      "twitter": "",
      "discord": "Maia#1234",
      "start_timestamp": 1650710045873
    },
    {
      "name": "Web Pundits",
      "twitter": "",
      "discord": "",
      "start_timestamp": 1602005184870
    },
    {
      "name": "Bjørn Nese",
      "twitter": "",
      "discord": "",
      "start_timestamp": 1579194404620
    },
    {
      "name": "Roman Chvanikoff",
      "twitter": "",
      "discord": "",
      "start_timestamp": 1554650361520
    },
    {
      "name": "Yagamii Society-Squad",
      "twitter": "",
      "discord": "",
      "start_timestamp": 1551197615762
    },
    {
      "name": "Tony James",
      "twitter": "tryhyperhost",
      "discord": "",
      "start_timestamp": 1540278599558
    },
    {
      "name": "Jon Yongfook",
      "twitter": "yongfook",
      "discord": "",
      "start_timestamp": 1514463320418
    },
    {
      "name": "Nazar ",
      "twitter": "nazar_io",
      "discord": "",
      "start_timestamp": 1511984104607
    },
    {
      "name": "Aaron ",
      "twitter": "aequasi",
      "discord": "",
      "start_timestamp": 1511242659284
    },
    {
      "name": "Garry Newman",
      "twitter": "garrynewman",
      "discord": "",
      "start_timestamp": 1511186868165
    },
    {
      "name": "Adrian Ocneanu",
      "twitter": "aocneanu",
      "discord": "",
      "start_timestamp": 1510731567799,
      "website_url": "https://www.earthlink.ro/",
      "website_name": "Earthlink"
    }
  ],
  "100": [
    {
      "name": "Richard Olsson",
      "twitter": "",
      "discord": "",
      "start_timestamp": 1675775477617
    },
    {
      "name": "David Matthews",
      "twitter": "",
      "discord": "",
      "start_timestamp": 1674556992338
    },
    {
      "name": "Viktoria Poddubetska",
      "twitter": "",
      "discord": "",
      "start_timestamp": 1672055776226
    },
    {
      "name": "Casino Zonder",
      "twitter": "",
      "discord": "",
      "start_timestamp": 1671099826607
    },
    {
      "name": "Casinos zonder Cruks",
      "twitter": "",
      "discord": "",
      "start_timestamp": 1671099122771
    },
    {
      "name": "Tom Eriksson",
      "twitter": "",
      "discord": "",
      "start_timestamp": 1670507550516
    },
    {
      "name": "Fora Fora24",
      "twitter": "",
      "discord": "",
      "start_timestamp": 1670327124145
    },
    {
      "name": "Qiang Lin",
      "twitter": "",
      "discord": "",
      "start_timestamp": 1669872263394
    },
    {
      "name": "haitham ashoo",
      "twitter": "",
      "discord": "",
      "start_timestamp": 1669728579021
    },
    {
      "name": "Sportonlinebetting.net",
      "twitter": "",
      "discord": "",
      "start_timestamp": 1668437357636
    },
    {
      "name": "Mark Taylor",
      "twitter": "",
      "discord": "",
      "start_timestamp": 1667996387582
    },
    {
      "name": "Viktoria Johansson",
      "twitter": "",
      "discord": "",
      "start_timestamp": 1667817711538
    },
    {
      "name": "Codeless.co",
      "twitter": "",
      "discord": "",
      "start_timestamp": 1667391083850
    },
    {
      "name": "Edward Amberton",
      "twitter": "",
      "discord": "",
      "start_timestamp": 1665083702202
    },
    {
      "name": "TradingWolf",
      "twitter": "",
      "discord": "Donnie Azoff#5330",
      "start_timestamp": 1665046036294
    },
    {
      "name": "Тимур Юхименко",
      "twitter": "",
      "discord": "",
      "start_timestamp": 1664442250904
    },
    {
      "name": "Stayatcasinos.com",
      "twitter": "",
      "discord": "",
      "start_timestamp": 1663060440289
    },
    {
      "name": "Genesis",
      "twitter": "",
      "discord": "",
      "start_timestamp": 1662013215446
    },
    {
      "name": "Iaroslav",
      "twitter": "",
      "discord": "",
      "start_timestamp": 1660635640997
    },
    {
      "name": "KingCasinoBonus",
      "twitter": "",
      "discord": "",
      "start_timestamp": 1658387047369
    },
    {
      "name": "Aktug Dogan",
      "twitter": "",
      "discord": "",
      "start_timestamp": 1658306729407
    },
    {
      "name": "CellTrackingApps",
      "twitter": "",
      "discord": "",
      "start_timestamp": 1657792735851
    },
    {
      "name": "Jolene White",
      "twitter": "",
      "discord": "",
      "start_timestamp": 1657431653161
    },
    {
      "name": "BSMG",
      "twitter": "",
      "discord": "",
      "start_timestamp": 1655906284177
    },
    {
      "name": "Limeup",
      "twitter": "",
      "discord": "",
      "start_timestamp": 1654695526778
    },
    {
      "name": "Mark john",
      "twitter": "",
      "discord": "",
      "start_timestamp": 1651872504158
    },
    {
      "name": "Isabella",
      "twitter": "",
      "discord": "",
      "start_timestamp": 1651840309587
    },
    {
      "name": "Mario",
      "twitter": "",
      "discord": "",
      "start_timestamp": 1651840297967
    },
    {
      "name": "Jim ",
      "twitter": "",
      "discord": "",
      "start_timestamp": 1651146518997
    },
    {
      "name": "Xoo",
      "twitter": "",
      "discord": "",
      "start_timestamp": 1650972172596
    },
    {
      "name": "Casinozondercruks.net",
      "twitter": "",
      "discord": "",
      "start_timestamp": 1650910703737
    },
    {
      "name": "D-Digital",
      "twitter": "",
      "discord": "",
      "start_timestamp": 1649178723170
    },
    {
      "name": "Aamir Javeed",
      "twitter": "",
      "discord": "",
      "start_timestamp": 1648635688308
    },
    {
      "name": "gavinlucas22",
      "twitter": "",
      "discord": "",
      "start_timestamp": 1646227588213
    },
    {
      "name": "Iaroslav Baklan",
      "twitter": "",
      "discord": "",
      "start_timestamp": 1644316856061
    },
    {
      "name": "Amelia Cook",
      "twitter": "",
      "discord": "",
      "start_timestamp": 1642157116722
    },
    {
      "name": "Khayriddin Sodiqov",
      "twitter": "",
      "discord": "",
      "start_timestamp": 1641032701064
    },
    {
      "name": "List.Casino",
      "twitter": "",
      "discord": "",
      "start_timestamp": 1640120508039
    },
    {
      "name": "PapersOwl ",
      "twitter": "",
      "discord": "",
      "start_timestamp": 1638881686598
    },
    {
      "name": "CasinosHunter",
      "twitter": "",
      "discord": "",
      "start_timestamp": 1638618432341
    },
    {
      "name": "seo pmi",
      "twitter": "",
      "discord": "",
      "start_timestamp": 1636622354871
    },
    {
      "name": "Viktor & Steve Scott (NonGamStopWager.com)",
      "twitter": "",
      "discord": "",
      "start_timestamp": 1636069062475
    },
    {
      "name": "Joe Kizlauskas",
      "twitter": "",
      "discord": "",
      "start_timestamp": 1634474912654
    },
    {
      "name": "TROYPOINT",
      "twitter": "",
      "discord": "",
      "start_timestamp": 1628531474200
    },
    {
      "name": "anton zlov",
      "twitter": "",
      "discord": "",
      "start_timestamp": 1627622523770
    },
    {
      "name": "Tuomas",
      "twitter": "",
      "discord": "",
      "start_timestamp": 1626770186595
    },
    {
      "name": "DEMETRIOU ANNA",
      "twitter": "",
      "discord": "",
      "start_timestamp": 1626433960625
    },
    {
      "name": "Harvey Walters",
      "twitter": "",
      "discord": "",
      "start_timestamp": 1625562084646
    },
    {
      "name": "Sarah Johnson",
      "twitter": "",
      "discord": "",
      "start_timestamp": 1623079667965
    },
    {
      "name": "Samuel Gramstad",
      "twitter": "",
      "discord": "Samz#0622",
      "start_timestamp": 1621672758292
    },
    {
      "name": "Anbefalt",
      "twitter": "",
      "discord": "",
      "start_timestamp": 1621615693000
    },
    {
      "name": "Gianni Museeuw",
      "twitter": "",
      "discord": "",
      "start_timestamp": 1620986834560
    },
    {
      "name": "PolskieKasynoHEX.org",
      "twitter": "",
      "discord": "",
      "start_timestamp": 1620836822427
    },
    {
      "name": "123Calendars",
      "twitter": "",
      "discord": "",
      "start_timestamp": 1604304762614
    },
    {
      "name": "Iaroslav Baklan",
      "twitter": "",
      "discord": "",
      "start_timestamp": 1603288719531
    },
    {
      "name": "Iaroslav Baklan",
      "twitter": "",
      "discord": "",
      "start_timestamp": 1603287724728
    },
    {
      "name": "Raj.bet",
      "twitter": "",
      "discord": "",
      "start_timestamp": 1598967631148
    },
    {
      "name": "Sanyo Digital",
      "twitter": "",
      "discord": "",
      "start_timestamp": 1593666554539
    },
    {
      "name": "James Muthuya",
      "twitter": "",
      "discord": "",
      "start_timestamp": 1592873359248
    },
    {
      "name": "MonoVM ",
      "twitter": "",
      "discord": "",
      "start_timestamp": 1588271410706
    },
    {
      "name": "Alex Green",
      "twitter": "",
      "discord": "",
      "start_timestamp": 1586410171626
    },
    {
      "name": "Fintan Costello",
      "twitter": "",
      "discord": "",
      "start_timestamp": 1584546730317
    },
    {
      "name": "BacklinksRocket ",
      "twitter": "",
      "discord": "",
      "start_timestamp": 1573141645092
    },
    {
      "name": "Iaroslav Baklan",
      "twitter": "",
      "discord": "",
      "start_timestamp": 1571294038349
    },
    {
      "name": "Mark Mazza",
      "twitter": "",
      "discord": "",
      "start_timestamp": 1566959843240
    },
    {
      "name": "Adela Belin",
      "twitter": "",
      "discord": "",
      "start_timestamp": 1564993835335
    },
    {
      "name": "Yiannakis Ttafounas",
      "twitter": "",
      "discord": "",
      "start_timestamp": 1564570532754
    },
    {
      "name": "Sparheld International GmbH",
      "twitter": "",
      "discord": "",
      "start_timestamp": 1563870141112
    },
    {
      "name": "usave ",
      "twitter": "",
      "discord": "",
      "start_timestamp": 1554906720385
    },
    {
      "name": "Robert Bolder",
      "twitter": "",
      "discord": "",
      "start_timestamp": 1546593784071
    },
    {
      "name": "HebergeurWeb.ca ",
      "twitter": "",
      "discord": "",
      "start_timestamp": 1544758597015
    },
    {
      "name": "CodeFirst ",
      "twitter": "",
      "discord": "",
      "start_timestamp": 1544398029162
    },
    {
      "name": "Phil Alves",
      "twitter": "philalves01",
      "discord": "",
      "start_timestamp": 1541989777176
    },
    {
      "name": "DontPayFull ",
      "twitter": "",
      "discord": "",
      "start_timestamp": 1535455908636
    },
    {
      "name": "Tooltwist ",
      "twitter": "",
      "discord": "",
      "start_timestamp": 1522552630215
    },
    {
      "name": "KeyCDN ",
      "twitter": "",
      "discord": "",
      "start_timestamp": 1520273212416
    }
  ],
  "300": [
    {
      "name": "PayDay Say",
      "twitter": "",
      "discord": "",
      "start_timestamp": 1677601273668
    },
    {
      "name": "Reza Shojaei",
      "twitter": "",
      "discord": "reza-shojaei#3469",
      "start_timestamp": 1657119340768
    },
    {
      "name": "siwagorn jungpol",
      "twitter": "",
      "discord": "",
      "start_timestamp": 1619886486801
    },
    {
      "name": "Leo Boost",
      "twitter": "",
      "discord": "",
      "start_timestamp": 1617550094768
    },
    {
      "name": "Alexander Haslam",
      "twitter": "",
      "discord": "indiealexh#1337",
      "start_timestamp": 1520399110272
    },
    {
      "name": "Ravi Gadesha",
      "twitter": "_9brainz",
      "discord": "",
      "start_timestamp": 1511089664533
    }
  ],
  "500": [
    {
      "name": "Tipe ",
      "twitter": "tipeio",
      "discord": "",
      "start_timestamp": 1524092319804
    }
  ]
}
